setup.py
invoicing/__init__.py
invoicing/invoice.py
pdfinv_generator.egg-info/PKG-INFO
pdfinv_generator.egg-info/SOURCES.txt
pdfinv_generator.egg-info/dependency_links.txt
pdfinv_generator.egg-info/requires.txt
pdfinv_generator.egg-info/top_level.txt