Metadata-Version: 2.1
Name: pdfinv-generator
Version: 1.0.0
Summary: This package converts Excel invoices to PDF invoices.
Home-page: https://example.com
Author: Ravi Konjeti
Author-email: ravikonjeti1234@gmail.com
License: MIT
Keywords: pdfinv,invoice,excel,pdf
Classifier: Development Status :: 3 - Alpha
Classifier: Intended Audience :: Developers
Classifier: Topic :: Software Development :: Build Tools
Classifier: License :: OSI Approved :: MIT License
Classifier: Programming Language :: Python :: 3.8
Classifier: Programming Language :: Python :: 3.9
Classifier: Programming Language :: Python :: 3.10
Classifier: Programming Language :: Python :: 3.11
